{
  "parent": "minecraft:recipes/root",
  "criteria": {
    "has_orange_jelly": {
      "conditions": {
        "items": [
          {
            "items": [
              "fruitsdelight:orange_jelly"
            ]
          }
        ]
      },
      "trigger": "minecraft:inventory_changed"
    },
    "has_the_recipe": {
      "conditions": {
        "recipe": "fruitsdelight:orange_jelly_block"
      },
      "trigger": "minecraft:recipe_unlocked"
    }
  },
  "requirements": [
    [
      "has_orange_jelly",
      "has_the_recipe"
    ]
  ],
  "rewards": {
    "recipes": [
      "fruitsdelight:orange_jelly_block"
    ]
  }
}