{
  "type": "minecraft:crafting_shapeless",
  "category": "misc",
  "ingredients": [
    {
      "item": "fruitsdelight:lemon_jam_block"
    },
    {
      "item": "minecraft:glass_bottle"
    },
    {
      "item": "minecraft:glass_bottle"
    },
    {
      "item": "minecraft:glass_bottle"
    },
    {
      "item": "minecraft:glass_bottle"
    },
    {
      "item": "minecraft:glass_bottle"
    },
    {
      "item": "minecraft:glass_bottle"
    },
    {
      "item": "minecraft:glass_bottle"
    },
    {
      "item": "minecraft:glass_bottle"
    }
  ],
  "result": {
    "count": 8,
    "id": "fruitsdelight:lemon_jam"
  }
}